Conversor/__init__.py
Conversor/convertir.py
Conversor-0.1.3.dist-info/METADATA
Conversor-0.1.3.dist-info/WHEEL
Conversor-0.1.3.dist-info/top_level.txt
Conversor-0.1.3.dist-info/RECORD
