Metadata-Version: 2.1
Name: Conversor
Version: 0.1.3
Summary: El objetivo de este proyecto es desarrollar una librería para Python que facilite la conversión de distintos tipos de medidas.
Home-page: https://github.com/gorkaelorriaga/nunez_elorriaga/
Author: Iker
Author-email: iker.nunez@alumni.mondragon.edu
Classifier: Development Status :: 3 - Alpha
Classifier: Intended Audience :: Developers
Classifier: License :: OSI Approved :: MIT License
Classifier: Programming Language :: Python :: 3
Classifier: Programming Language :: Python :: 3.6
Classifier: Programming Language :: Python :: 3.7
Classifier: Programming Language :: Python :: 3.8
Classifier: Programming Language :: Python :: 3.9
Classifier: Topic :: Software Development :: Libraries :: Python Modules
Requires-Dist: requests
